LICENSE.txt
README.txt
kpconsole.py
setup.cfg
setup.py
docs/HISTORY.txt
kpconsole.egg-info/PKG-INFO
kpconsole.egg-info/SOURCES.txt
kpconsole.egg-info/dependency_links.txt
kpconsole.egg-info/entry_points.txt
kpconsole.egg-info/requires.txt
kpconsole.egg-info/top_level.txt
kpconsole.egg-info/zip-safe