Metadata-Version: 1.0
Name: kpconsole
Version: 1.0.2
Summary: Smart-M3 KP console for interactive testing and debugging
Home-page: http://asibsync.sourceforge.net
Author: Eemeli Kantola
Author-email: eemeli.kantola@iki.fi
License: BSD
Keywords: m3 sib kp console
Platform: UNKNOWN
Classifier: Development Status :: 4 - Beta
Classifier: Environment :: Console
Classifier: Intended Audience :: Developers
Classifier: Programming Language :: Python :: 2.6
Classifier: Topic :: Internet
